README.md
setup.cfg
setup.py
mdev_gaussian_binomial_distributions/Binomialdistribution.py
mdev_gaussian_binomial_distributions/Gaussiandistribution.py
mdev_gaussian_binomial_distributions/Generaldistribution.py
mdev_gaussian_binomial_distributions/__init__.py
mdev_gaussian_binomial_distributions.egg-info/PKG-INFO
mdev_gaussian_binomial_distributions.egg-info/SOURCES.txt
mdev_gaussian_binomial_distributions.egg-info/dependency_links.txt
mdev_gaussian_binomial_distributions.egg-info/not-zip-safe
mdev_gaussian_binomial_distributions.egg-info/top_level.txt