Metadata-Version: 1.0
Name: mdev-gaussian-binomial-distributions
Version: 0.3
Summary: Gaussian and Binomial distributions
Home-page: UNKNOWN
Author: UNKNOWN
Author-email: UNKNOWN
License: UNKNOWN
Platform: UNKNOWN
